hammer/common/__init__.py
hammer/common/cadence/__init__.py
hammer/common/cadence/defaults.yml
hammer/common/cadence/defaults_types.yml
hammer/common/mentor/__init__.py
hammer/common/mentor/defaults.yml
hammer/common/mentor/defaults_types.yml
hammer/common/openroad/__init__.py
hammer/common/openroad/defaults.yml
hammer/common/openroad/defaults_types.yml
hammer/common/synopsys/__init__.py
hammer/common/synopsys/defaults.yml
hammer/common/synopsys/defaults_types.yml
hammer/common/vivado/vivado_core.py
hammer/config/__init__.py
hammer/config/builtins.yml
hammer/config/common.py
hammer/config/config_src.py
hammer/config/defaults.yml
hammer/config/defaults_types.yml
hammer/config/yaml2json.py
hammer/drc/icv/README.md
hammer/drc/icv/__init__.py
hammer/drc/icv/defaults.yml
hammer/drc/klayout/__init__.py
hammer/drc/klayout/default_types.yml
hammer/drc/klayout/defaults.yml
hammer/drc/magic/__init__.py
hammer/drc/magic/defaults.yml
hammer/drc/mockdrc/__init__.py
hammer/drc/nop/__init__.py
hammer/drc/openroad/__init__.py
hammer/drc/openroad/defaults.yml
hammer/drc/pegasus/README.md
hammer/drc/pegasus/__init__.py
hammer/drc/pegasus/defaults.yml
hammer/drc/pegasus/defaults_types.yml
hammer/formal/conformal/__init__.py
hammer/formal/conformal/defaults.yml
hammer/generate_properties.py
hammer/logging/__init__.py
hammer/logging/logging.py
hammer/logging/test.py
hammer/lvs/icv/__init__.py
hammer/lvs/icv/defaults.yml
hammer/lvs/mocklvs/__init__.py
hammer/lvs/netgen/__init__.py
hammer/lvs/netgen/defaults.yml
hammer/lvs/nop/__init__.py
hammer/lvs/pegasus/__init__.py
hammer/lvs/pegasus/defaults.yml
hammer/lvs/pegasus/defaults_types.yml
hammer/par/innovus/__init__.py
hammer/par/innovus/defaults.yml
hammer/par/innovus/dump_stackup_to_json.tcl
hammer/par/mockpar/__init__.py
hammer/par/mockpar/defaults.yml
hammer/par/nop/__init__.py
hammer/par/openroad/README.md
hammer/par/openroad/__init__.py
hammer/par/openroad/defaults.yml
hammer/par/openroad/defaults_types.yml
hammer_vlsi-1.2.0.dist-info/LICENSE
hammer_vlsi-1.2.0.dist-info/METADATA
hammer_vlsi-1.2.0.dist-info/WHEEL
hammer_vlsi-1.2.0.dist-info/entry_points.txt
hammer_vlsi-1.2.0.dist-info/RECORD
