Metadata-Version: 2.1
Name: hammer-vlsi
Version: 1.2.0
Summary: Hammer is a physical design framework that wraps around vendor specific technologies and tools to provide a single API to create ASICs.
Home-page: https://github.com/ucb-bar/hammer
Author: Colin Schmidt
Author-email: colin.schmidt@sifive.com
Maintainer: Harrison Liew
Maintainer-email: harrisonliew@berkeley.edu
Requires-Python: >=3.9,<4.0
Classifier: Programming Language :: Python :: 3
Classifier: Programming Language :: Python :: 3.9
Classifier: Programming Language :: Python :: 3.10
Classifier: Programming Language :: Python :: 3.11
Provides-Extra: asap7
Provides-Extra: asap7-gdstk
Requires-Dist: PyYAML (>=6.0,<7.0)
Requires-Dist: gdspy (==1.4) ; extra == "asap7"
Requires-Dist: gdstk (>=0.9.0,<0.10.0) ; extra == "asap7-gdstk"
Requires-Dist: numpy (>=1.23.0,<2.0.0)
Requires-Dist: pydantic (>=1.9.2,<2.0.0)
Requires-Dist: ruamel.yaml (>=0.17.21,<0.18.0)
Project-URL: Repository, https://github.com/ucb-bar/hammer
